{
  "note_type": "(Absplayer) Anki Note Type by Admin Phúc",
  "deck": "Bulk Card Creator",
  "match_field": null,
  "created": 1,
  "updated": 0,
  "warnings": [],
  "write_guid_backfill": true,
  "cards": [
    {
      "Sentence": "insert_your_content_here",
      "Definition": "insert_your_content_here",
      "Word": "insert_your_content_here",
      "Audio": "insert_your_content_here",
      "Image": "insert_your_content_here",
      "Source": "insert_your_content_here",
      "URL": "insert_your_content_here",
      "Subtitle Track 1": "insert_your_content_here",
      "Subtitle Track 2": "insert_your_content_here",
      "Subtitle Track 3": "insert_your_content_here",
      "__guid__": "B)8({u{9{m"
    }
  ],
  "timestamp": "2026-04-07T16:52:37"
}